{
  "displayOrder": 800,
  "artistName": "Dafné Kritharas",
  "slug": "dafne-kritharas",
  "category": [
    "Live"
  ],
  "biography": "Dafné Kritharas dévoile son univers à travers des créations originales en grec et en français, dans un inclassable croisement de styles entre Moyen-Orient, jazz et classique frôlé d'une étrange électro tantôt inquiétante, tantôt festive, tantôt les deux. Dafné Kritharas chante l’exil, l’amour et la joie des chants grecs d’antan.\n\nDans son monde allégorique et intemporel, la réalité est sublimée. Les histoires vraies sont transformées en contes mystérieux où les femmes bafouées deviennent de redoutables reines des montagnes, où la mer grondante protège les opprimés, où le péché s'unit à la prière pour engendrer le pardon.\n\nAccompagnée sur scène de 5 musiciens (percussions, cordes, instruments à vents), venez découvrir cette création inédite et solaire qui unit l’intime à l’orchestral, le mystique au grandiose.\n\n**Booking : yohann@bluebird-booking.eu**\n\n\\\nP﻿hoto : Chloé Kritharas Devienne",
  "citation": {
    "quote": "« Qu’elle chante une mélodie grecque, bosniaque, arménienne ou turque, Dafné Kritharas le fait toujours avec la même justesse et intensité. La chanteuse raconte des histoires venues d’ailleurs, des contes et légendes traditionnelles avec une voix impressionnante, ensorcelante. Dafné Kritharas est un peu sorcière, un peu magicienne, un peu déesse, grecque évidemment. (…) » – France Musique",
    "quoteImage": "/static/assets/quote/dafne-kritharas/dafne-banner-1.jpg"
  },
  "introduction": "En concert à La Cigale le 18 mars 2024 / En tournée en 2024-2025",
  "banner": "/static/assets/banner/dafne-kritharas/dafne-square-1.jpg"
}